a_pandas_ex_logsplit/LICENSE
a_pandas_ex_logsplit/README.MD
a_pandas_ex_logsplit/__init__.py
a_pandas_ex_logsplit/requirements.txt
a_pandas_ex_logsplit/thirdparty.json
a_pandas_ex_logsplit-0.10.dist-info/LICENSE.rst
a_pandas_ex_logsplit-0.10.dist-info/METADATA
a_pandas_ex_logsplit-0.10.dist-info/WHEEL
a_pandas_ex_logsplit-0.10.dist-info/top_level.txt
a_pandas_ex_logsplit-0.10.dist-info/RECORD
